{
    "plot_type": "time_v_point_margin",
    "title": "% Chance of Coming Back Deficit Versus Time",
    "min_x": 1,
    "max_x": 24,
    "x_label": "Minutes Remaining",
    "y_label": "Points Down",
    "calculate_occurrences": false,
    "y_ticks": [
        -19,
        -17,
        -15,
        -13,
        -11,
        -9,
        -7,
        -5,
        -3
    ],
    "y_tick_labels": [
        -19,
        -17,
        -15,
        -13,
        -11,
        -9,
        -7,
        -5,
        -3
    ],
    "lines": [
        {
            "legend": "10% | 1996-97 to 2016-17 (26483 Games)",
            "number_of_games": 26483,
            "x_values": [
                24,
                23,
                22,
                21,
                20,
                19,
                18,
                17,
                16,
                15,
                14,
                13,
                12,
                11,
                10,
                9,
                8,
                7,
                6,
                5,
                4,
                3,
                2,
                1
            ],
            "y_values": [
                {
                    "win_count": 71,
                    "loss_count": 609,
                    "win_plus_loss_count": 680.0,
                    "game_count": 680.0,
                    "point_margin_occurs_percent": 0.025676849299550657,
                    "percent": 0.10441176470588236,
                    "x_value": 24,
                    "y_value": -15,
                    "y_fit_value": -14.414993959095373
                },
                {
                    "win_count": 58,
                    "loss_count": 630,
                    "win_plus_loss_count": 688.0,
                    "game_count": 688.0,
                    "point_margin_occurs_percent": 0.02597892987954537,
                    "percent": 0.08430232558139535,
                    "x_value": 23,
                    "y_value": -15,
                    "y_fit_value": -14.435390305088417
                },
                {
                    "win_count": 49,
                    "loss_count": 633,
                    "win_plus_loss_count": 682.0,
                    "game_count": 682.0,
                    "point_margin_occurs_percent": 0.025752369444549332,
                    "percent": 0.0718475073313783,
                    "x_value": 22,
                    "y_value": -15,
                    "y_fit_value": -14.07034522330165
                },
                {
                    "win_count": 76,
                    "loss_count": 737,
                    "win_plus_loss_count": 813.0,
                    "game_count": 813.0,
                    "point_margin_occurs_percent": 0.03069893894196277,
                    "percent": 0.09348093480934809,
                    "x_value": 21,
                    "y_value": -14,
                    "y_fit_value": -13.7656132606859
                },
                {
                    "win_count": 63,
                    "loss_count": 736,
                    "win_plus_loss_count": 799.0,
                    "game_count": 799.0,
                    "point_margin_occurs_percent": 0.03017029792697202,
                    "percent": 0.07884856070087609,
                    "x_value": 20,
                    "y_value": -14,
                    "y_fit_value": -13.374705006261468
                },
                {
                    "win_count": 73,
                    "loss_count": 777,
                    "win_plus_loss_count": 850.0,
                    "game_count": 850.0,
                    "point_margin_occurs_percent": 0.032096061624438316,
                    "percent": 0.08588235294117647,
                    "x_value": 19,
                    "y_value": -14,
                    "y_fit_value": -13.10725674755489
                },
                {
                    "win_count": 76,
                    "loss_count": 876,
                    "win_plus_loss_count": 952.0,
                    "game_count": 952.0,
                    "point_margin_occurs_percent": 0.03594758901937092,
                    "percent": 0.07983193277310924,
                    "x_value": 18,
                    "y_value": -13,
                    "y_fit_value": -12.804987446284265
                },
                {
                    "win_count": 71,
                    "loss_count": 843,
                    "win_plus_loss_count": 914.0,
                    "game_count": 914.0,
                    "point_margin_occurs_percent": 0.03451270626439603,
                    "percent": 0.07768052516411379,
                    "x_value": 17,
                    "y_value": -13,
                    "y_fit_value": -12.487258537453261
                },
                {
                    "win_count": 69,
                    "loss_count": 848,
                    "win_plus_loss_count": 917.0,
                    "game_count": 917.0,
                    "point_margin_occurs_percent": 0.03462598648189404,
                    "percent": 0.0752453653217012,
                    "x_value": 16,
                    "y_value": -13,
                    "y_fit_value": -12.053330950646396
                },
                {
                    "win_count": 98,
                    "loss_count": 937,
                    "win_plus_loss_count": 1035.0,
                    "game_count": 1035.0,
                    "point_margin_occurs_percent": 0.03908167503681607,
                    "percent": 0.09468599033816426,
                    "x_value": 15,
                    "y_value": -12,
                    "y_fit_value": -11.78999341356825
                },
                {
                    "win_count": 69,
                    "loss_count": 914,
                    "win_plus_loss_count": 983.0,
                    "game_count": 983.0,
                    "point_margin_occurs_percent": 0.03711815126685043,
                    "percent": 0.07019328585961343,
                    "x_value": 14,
                    "y_value": -12,
                    "y_fit_value": -11.403332287885622
                },
                {
                    "win_count": 100,
                    "loss_count": 993,
                    "win_plus_loss_count": 1093.0,
                    "game_count": 1093.0,
                    "point_margin_occurs_percent": 0.04127175924177774,
                    "percent": 0.09149130832570906,
                    "x_value": 13,
                    "y_value": -11,
                    "y_fit_value": -10.998177991724003
                },
                {
                    "win_count": 105,
                    "loss_count": 1045,
                    "win_plus_loss_count": 1150.0,
                    "game_count": 1150.0,
                    "point_margin_occurs_percent": 0.04342408337424008,
                    "percent": 0.09130434782608696,
                    "x_value": 12,
                    "y_value": -11,
                    "y_fit_value": -10.487340478352833
                },
                {
                    "win_count": 95,
                    "loss_count": 986,
                    "win_plus_loss_count": 1081.0,
                    "game_count": 1081.0,
                    "point_margin_occurs_percent": 0.040818638371785676,
                    "percent": 0.08788159111933395,
                    "x_value": 11,
                    "y_value": -11,
                    "y_fit_value": -10.144706197671178
                },
                {
                    "win_count": 103,
                    "loss_count": 1060,
                    "win_plus_loss_count": 1163.0,
                    "game_count": 1163.0,
                    "point_margin_occurs_percent": 0.04391496431673149,
                    "percent": 0.0885640584694755,
                    "x_value": 10,
                    "y_value": -10,
                    "y_fit_value": -9.657970439284348
                },
                {
                    "win_count": 95,
                    "loss_count": 1121,
                    "win_plus_loss_count": 1216.0,
                    "game_count": 1216.0,
                    "point_margin_occurs_percent": 0.04591624815919647,
                    "percent": 0.078125,
                    "x_value": 9,
                    "y_value": -10,
                    "y_fit_value": -9.243802023293087
                },
                {
                    "win_count": 123,
                    "loss_count": 1214,
                    "win_plus_loss_count": 1337.0,
                    "game_count": 1337.0,
                    "point_margin_occurs_percent": 0.050485216931616506,
                    "percent": 0.09199700822737472,
                    "x_value": 8,
                    "y_value": -9,
                    "y_fit_value": -8.862199068227415
                },
                {
                    "win_count": 105,
                    "loss_count": 1122,
                    "win_plus_loss_count": 1227.0,
                    "game_count": 1227.0,
                    "point_margin_occurs_percent": 0.046331608956689196,
                    "percent": 0.08557457212713937,
                    "x_value": 7,
                    "y_value": -9,
                    "y_fit_value": -8.287896865301592
                },
                {
                    "win_count": 125,
                    "loss_count": 1214,
                    "win_plus_loss_count": 1339.0,
                    "game_count": 1339.0,
                    "point_margin_occurs_percent": 0.05056073707661519,
                    "percent": 0.09335324869305452,
                    "x_value": 6,
                    "y_value": -8,
                    "y_fit_value": -7.721177588137798
                },
                {
                    "win_count": 99,
                    "loss_count": 1213,
                    "win_plus_loss_count": 1312.0,
                    "game_count": 1312.0,
                    "point_margin_occurs_percent": 0.04954121511913303,
                    "percent": 0.07545731707317073,
                    "x_value": 5,
                    "y_value": -8,
                    "y_fit_value": -7.196045383883253
                },
                {
                    "win_count": 129,
                    "loss_count": 1291,
                    "win_plus_loss_count": 1420.0,
                    "game_count": 1420.0,
                    "point_margin_occurs_percent": 0.05361930294906166,
                    "percent": 0.09084507042253522,
                    "x_value": 4,
                    "y_value": -7,
                    "y_fit_value": -6.445304655062646
                },
                {
                    "win_count": 133,
                    "loss_count": 1330,
                    "win_plus_loss_count": 1463.0,
                    "game_count": 1463.0,
                    "point_margin_occurs_percent": 0.055242986066533245,
                    "percent": 0.09090909090909091,
                    "x_value": 3,
                    "y_value": -6,
                    "y_fit_value": -5.67571376758897
                },
                {
                    "win_count": 162,
                    "loss_count": 1318,
                    "win_plus_loss_count": 1480.0,
                    "game_count": 1480.0,
                    "point_margin_occurs_percent": 0.05588490729902201,
                    "percent": 0.10945945945945947,
                    "x_value": 2,
                    "y_value": -5,
                    "y_fit_value": -4.83288694541451
                },
                {
                    "win_count": 126,
                    "loss_count": 1460,
                    "win_plus_loss_count": 1586.0,
                    "game_count": 1586.0,
                    "point_margin_occurs_percent": 0.05988747498395197,
                    "percent": 0.07944514501891552,
                    "x_value": 1,
                    "y_value": -4,
                    "y_fit_value": -3.645351228283146
                }
            ]
        },
        {
            "legend": "10% | 2017-18 to 2024-25 (9925 Games)",
            "number_of_games": 9925,
            "x_values": [
                24,
                23,
                22,
                21,
                20,
                19,
                18,
                17,
                16,
                15,
                14,
                13,
                12,
                11,
                10,
                9,
                8,
                7,
                6,
                5,
                4,
                3,
                2,
                1
            ],
            "y_values": [
                {
                    "win_count": 20,
                    "loss_count": 163,
                    "win_plus_loss_count": 183.0,
                    "game_count": 183.0,
                    "point_margin_occurs_percent": 0.018438287153652394,
                    "percent": 0.1092896174863388,
                    "x_value": 24,
                    "y_value": -18,
                    "y_fit_value": -17.067451705706794
                },
                {
                    "win_count": 26,
                    "loss_count": 214,
                    "win_plus_loss_count": 240.0,
                    "game_count": 240.0,
                    "point_margin_occurs_percent": 0.024181360201511334,
                    "percent": 0.10833333333333334,
                    "x_value": 23,
                    "y_value": -17,
                    "y_fit_value": -16.483267715545505
                },
                {
                    "win_count": 21,
                    "loss_count": 240,
                    "win_plus_loss_count": 261.0,
                    "game_count": 261.0,
                    "point_margin_occurs_percent": 0.026297229219143577,
                    "percent": 0.08045977011494253,
                    "x_value": 22,
                    "y_value": -16,
                    "y_fit_value": -16.03362113517213
                },
                {
                    "win_count": 34,
                    "loss_count": 267,
                    "win_plus_loss_count": 301.0,
                    "game_count": 301.0,
                    "point_margin_occurs_percent": 0.030327455919395466,
                    "percent": 0.11295681063122924,
                    "x_value": 21,
                    "y_value": -16,
                    "y_fit_value": -15.711713632269126
                },
                {
                    "win_count": 26,
                    "loss_count": 252,
                    "win_plus_loss_count": 278.0,
                    "game_count": 278.0,
                    "point_margin_occurs_percent": 0.02801007556675063,
                    "percent": 0.09352517985611511,
                    "x_value": 20,
                    "y_value": -15,
                    "y_fit_value": -15.421347551834865
                },
                {
                    "win_count": 25,
                    "loss_count": 213,
                    "win_plus_loss_count": 238.0,
                    "game_count": 238.0,
                    "point_margin_occurs_percent": 0.02397984886649874,
                    "percent": 0.10504201680672269,
                    "x_value": 19,
                    "y_value": -16,
                    "y_fit_value": -15.121560255345138
                },
                {
                    "win_count": 29,
                    "loss_count": 278,
                    "win_plus_loss_count": 307.0,
                    "game_count": 307.0,
                    "point_margin_occurs_percent": 0.03093198992443325,
                    "percent": 0.09446254071661238,
                    "x_value": 18,
                    "y_value": -14,
                    "y_fit_value": -14.627663541684335
                },
                {
                    "win_count": 29,
                    "loss_count": 276,
                    "win_plus_loss_count": 305.0,
                    "game_count": 305.0,
                    "point_margin_occurs_percent": 0.030730478589420653,
                    "percent": 0.09508196721311475,
                    "x_value": 17,
                    "y_value": -15,
                    "y_fit_value": -14.012439554632586
                },
                {
                    "win_count": 31,
                    "loss_count": 312,
                    "win_plus_loss_count": 343.0,
                    "game_count": 343.0,
                    "point_margin_occurs_percent": 0.03455919395465995,
                    "percent": 0.09037900874635568,
                    "x_value": 16,
                    "y_value": -14,
                    "y_fit_value": -13.665616803386662
                },
                {
                    "win_count": 29,
                    "loss_count": 321,
                    "win_plus_loss_count": 350.0,
                    "game_count": 350.0,
                    "point_margin_occurs_percent": 0.03526448362720403,
                    "percent": 0.08285714285714285,
                    "x_value": 15,
                    "y_value": -13,
                    "y_fit_value": -13.315917352849095
                },
                {
                    "win_count": 35,
                    "loss_count": 334,
                    "win_plus_loss_count": 369.0,
                    "game_count": 369.0,
                    "point_margin_occurs_percent": 0.03717884130982368,
                    "percent": 0.0948509485094851,
                    "x_value": 14,
                    "y_value": -13,
                    "y_fit_value": -12.825301081909286
                },
                {
                    "win_count": 28,
                    "loss_count": 314,
                    "win_plus_loss_count": 342.0,
                    "game_count": 342.0,
                    "point_margin_occurs_percent": 0.03445843828715365,
                    "percent": 0.08187134502923976,
                    "x_value": 13,
                    "y_value": -13,
                    "y_fit_value": -12.221825849535175
                },
                {
                    "win_count": 37,
                    "loss_count": 379,
                    "win_plus_loss_count": 416.0,
                    "game_count": 416.0,
                    "point_margin_occurs_percent": 0.04191435768261965,
                    "percent": 0.0889423076923077,
                    "x_value": 12,
                    "y_value": -12,
                    "y_fit_value": -11.53970147708469
                },
                {
                    "win_count": 37,
                    "loss_count": 357,
                    "win_plus_loss_count": 394.0,
                    "game_count": 394.0,
                    "point_margin_occurs_percent": 0.03969773299748111,
                    "percent": 0.09390862944162437,
                    "x_value": 11,
                    "y_value": -11,
                    "y_fit_value": -10.970158347507269
                },
                {
                    "win_count": 46,
                    "loss_count": 408,
                    "win_plus_loss_count": 454.0,
                    "game_count": 454.0,
                    "point_margin_occurs_percent": 0.04574307304785894,
                    "percent": 0.1013215859030837,
                    "x_value": 10,
                    "y_value": -10,
                    "y_fit_value": -10.453870376738486
                },
                {
                    "win_count": 31,
                    "loss_count": 399,
                    "win_plus_loss_count": 430.0,
                    "game_count": 430.0,
                    "point_margin_occurs_percent": 0.04332493702770781,
                    "percent": 0.07209302325581396,
                    "x_value": 9,
                    "y_value": -11,
                    "y_fit_value": -10.064400120527669
                },
                {
                    "win_count": 32,
                    "loss_count": 406,
                    "win_plus_loss_count": 438.0,
                    "game_count": 438.0,
                    "point_margin_occurs_percent": 0.044130982367758184,
                    "percent": 0.0730593607305936,
                    "x_value": 8,
                    "y_value": -9,
                    "y_fit_value": -9.639268582155783
                },
                {
                    "win_count": 34,
                    "loss_count": 413,
                    "win_plus_loss_count": 447.0,
                    "game_count": 447.0,
                    "point_margin_occurs_percent": 0.04503778337531486,
                    "percent": 0.07606263982102908,
                    "x_value": 7,
                    "y_value": -10,
                    "y_fit_value": -9.161618973407597
                },
                {
                    "win_count": 30,
                    "loss_count": 389,
                    "win_plus_loss_count": 419.0,
                    "game_count": 419.0,
                    "point_margin_occurs_percent": 0.04221662468513854,
                    "percent": 0.07159904534606205,
                    "x_value": 6,
                    "y_value": -9,
                    "y_fit_value": -8.672012995253152
                },
                {
                    "win_count": 52,
                    "loss_count": 433,
                    "win_plus_loss_count": 485.0,
                    "game_count": 485.0,
                    "point_margin_occurs_percent": 0.048866498740554154,
                    "percent": 0.10721649484536082,
                    "x_value": 5,
                    "y_value": -8,
                    "y_fit_value": -7.75404200260036
                },
                {
                    "win_count": 51,
                    "loss_count": 412,
                    "win_plus_loss_count": 463.0,
                    "game_count": 463.0,
                    "point_margin_occurs_percent": 0.04664987405541562,
                    "percent": 0.1101511879049676,
                    "x_value": 4,
                    "y_value": -7,
                    "y_fit_value": -6.989778665585732
                },
                {
                    "win_count": 41,
                    "loss_count": 457,
                    "win_plus_loss_count": 498.0,
                    "game_count": 498.0,
                    "point_margin_occurs_percent": 0.05017632241813602,
                    "percent": 0.0823293172690763,
                    "x_value": 3,
                    "y_value": -7,
                    "y_fit_value": -6.136987208401977
                },
                {
                    "win_count": 38,
                    "loss_count": 459,
                    "win_plus_loss_count": 497.0,
                    "game_count": 497.0,
                    "point_margin_occurs_percent": 0.05007556675062972,
                    "percent": 0.07645875251509054,
                    "x_value": 2,
                    "y_value": -6,
                    "y_fit_value": -5.0747262165096565
                },
                {
                    "win_count": 39,
                    "loss_count": 477,
                    "win_plus_loss_count": 516.0,
                    "game_count": 516.0,
                    "point_margin_occurs_percent": 0.051989924433249374,
                    "percent": 0.0755813953488372,
                    "x_value": 1,
                    "y_value": -4,
                    "y_fit_value": -3.8372347994356337
                }
            ]
        }
    ]
}